dankert/__init__.py
dankert/__main__.py
dankert-0.1.dist-info/METADATA
dankert-0.1.dist-info/WHEEL
dankert-0.1.dist-info/entry_points.txt
dankert-0.1.dist-info/top_level.txt
dankert-0.1.dist-info/RECORD
