Metadata-Version: 2.4
Name: dankert
Version: 0.1
Summary: Легендарная CLI-команда от DanKert
Author: DanKert
Requires-Python: >=3.6
Dynamic: author
Dynamic: description
Dynamic: description-content-type
Dynamic: requires-python
Dynamic: summary
